simple_translate/__init__.py
simple_translate/simple_translate.py
simple_translate/supported_languages.py
simple_translate-0.1.6.dist-info/LICENSE
simple_translate-0.1.6.dist-info/METADATA
simple_translate-0.1.6.dist-info/WHEEL
simple_translate-0.1.6.dist-info/top_level.txt
simple_translate-0.1.6.dist-info/RECORD
