Metadata-Version: 2.1
Name: simple_translate
Version: 0.1.6
Summary: Multi language translator
Home-page: https://github.com/usmonovshohruxmirzo/easy-translate
Author: Usmonov Shoxruxmirzo
Author-email: usmonovshohruxmirzo@gmail.com
Classifier: Programming Language :: Python :: 3
Classifier: License :: OSI Approved :: MIT License
Classifier: Operating System :: OS Independent
Requires-Python: >=3.6
License-File: LICENSE
